{"id": "1666163029", "isEnabled": true, "objectTypeId": "0-3", "flowType": "WORKFLOW", "revisionId": "6", "name": "Date Stamp | PBSR Submit Date", "description": "Sets the submit date when the status is \"Submitted\" and the submit date is not already set.", "uuid": "Date Stamp | PBSR Submit Date-1666163029", "createdAt": "2025-06-26T20:17:23.829Z", "updatedAt": "2025-10-15T21:56:27.164Z", "startActionId": "9", "nextAvailableActionId": "10", "actions": [{"actionId": "9", "actionTypeVersion": 0, "actionTypeId": "0-5", "fields": {"property_name": "pbsr_submit_date", "value": {"timestampType": "EXECUTION_TIME", "type": "TIMESTAMP"}}, "type": "SINGLE_CONNECTION"}], "enrollmentCriteria": {"shouldReEnroll": false, "listFilterBranch": {"filterBranches": [{"filterBranches": [], "filters": [{"property": "pbsr_incentive_status", "operation": {"operator": "IS_ANY_OF", "includeObjectsWithNoValueSet": false, "values": ["Submitted"], "operationType": "ENUMERATION"}, "filterType": "PROPERTY"}, {"property": "pbsr_submit_date", "operation": {"operator": "IS_UNKNOWN", "includeObjectsWithNoValueSet": false, "operationType": "ALL_PROPERTY"}, "filterType": "PROPERTY"}], "filterBranchType": "AND", "filterBranchOperator": "AND"}], "filters": [], "filterBranchType": "OR", "filterBranchOperator": "OR"}, "unEnrollObjectsNotMeetingCriteria": false, "reEnrollmentTriggersFilterBranches": [], "type": "LIST_BASED"}, "timeWindows": [], "blockedDates": [], "customProperties": {}, "dataSources": [{"name": "fetched_object_149673143", "objectTypeId": "0-2", "associationTypeId": 341, "associationCategory": "HUBSPOT_DEFINED", "sortBy": {"property": "hs_lastmodifieddate", "missing": null, "order": "DESC"}, "type": "ASSOCIATION"}, {"name": "fetched_object_149673141", "objectTypeId": "0-1", "associationTypeId": 3, "associationCategory": "HUBSPOT_DEFINED", "type": "ASSOCIATION"}, {"name": "fetched_object_149673144", "objectTypeId": "0-8", "associationTypeId": 19, "associationCategory": "HUBSPOT_DEFINED", "sortBy": {"property": "hs_lastmodifieddate", "missing": null, "order": "DESC"}, "type": "ASSOCIATION"}, {"name": "fetched_object_149673142", "objectTypeId": "0-1", "associationTypeId": 3, "associationCategory": "HUBSPOT_DEFINED", "sortBy": {"property": "hs_lastmodifieddate", "missing": null, "order": "DESC"}, "type": "ASSOCIATION"}], "crmObjectCreationStatus": "COMPLETE", "type": "PLATFORM_FLOW"}