{"id": "1669561013", "isEnabled": false, "objectTypeId": "0-3", "flowType": "WORKFLOW", "revisionId": "16", "name": "08b. Design Flow - New Construction Design In Progress", "description": "Updates the design status to \"In Progress\" when a related task titled \"Retrieve Info for New Construction Design Plans - ZRS\" is completed.", "uuid": "08b. Design Flow - New Construction Design In Progress-1669561013", "createdAt": "2025-07-08T00:41:15.431Z", "updatedAt": "2026-05-13T23:26:04.840Z", "startActionId": "2", "nextAvailableActionId": "3", "actions": [{"actionId": "2", "actionTypeVersion": 0, "actionTypeId": "0-5", "fields": {"property_name": "design_status", "value": {"staticValue": "In Progress", "type": "STATIC_VALUE"}}, "type": "SINGLE_CONNECTION"}], "enrollmentCriteria": {"shouldReEnroll": false, "listFilterBranch": {"filterBranches": [{"filterBranches": [{"filterBranches": [], "filters": [{"property": "hs_task_subject", "operation": {"operator": "IS_EQUAL_TO", "includeObjectsWithNoValueSet": false, "values": ["Retrieve Info for New Construction Design Plans - ZRS"], "operationType": "MULTISTRING"}, "filterType": "PROPERTY"}, {"property": "hs_task_status", "operation": {"operator": "IS_ANY_OF", "includeObjectsWithNoValueSet": false, "values": ["COMPLETED"], "operationType": "ENUMERATION"}, "filterType": "PROPERTY"}], "objectTypeId": "0-4", "operator": "IN_LIST", "associationTypeId": 11, "associationCategory": "HUBSPOT_DEFINED", "filterBranchType": "ASSOCIATION", "filterBranchOperator": "AND"}], "filters": [], "filterBranchType": "AND", "filterBranchOperator": "AND"}], "filters": [], "filterBranchType": "OR", "filterBranchOperator": "OR"}, "unEnrollObjectsNotMeetingCriteria": false, "reEnrollmentTriggersFilterBranches": [], "type": "LIST_BASED"}, "timeWindows": [], "blockedDates": [], "customProperties": {}, "dataSources": [{"name": "fetched_object_152831080", "objectTypeId": "0-2", "associationTypeId": 341, "associationCategory": "HUBSPOT_DEFINED", "sortBy": {"property": "hs_lastmodifieddate", "missing": null, "order": "DESC"}, "type": "ASSOCIATION"}, {"name": "fetched_object_152831081", "objectTypeId": "0-8", "associationTypeId": 19, "associationCategory": "HUBSPOT_DEFINED", "sortBy": {"property": "hs_lastmodifieddate", "missing": null, "order": "DESC"}, "type": "ASSOCIATION"}, {"name": "fetched_object_152831078", "objectTypeId": "0-1", "associationTypeId": 3, "associationCategory": "HUBSPOT_DEFINED", "sortBy": {"property": "hs_lastmodifieddate", "missing": null, "order": "DESC"}, "type": "ASSOCIATION"}, {"name": "fetched_object_152831079", "objectTypeId": "0-1", "associationTypeId": 3, "associationCategory": "HUBSPOT_DEFINED", "type": "ASSOCIATION"}], "crmObjectCreationStatus": "COMPLETE", "type": "PLATFORM_FLOW"}