{"id": "1669696925", "isEnabled": true, "objectTypeId": "0-3", "flowType": "WORKFLOW", "revisionId": "7", "name": "06b. Permit Flow - 2nd Permit Rejected", "description": "Updates the design status to \"Revision Needed - Rejected by AHJ\" and sends an internal email when the permitting status is \"Rejected - Needs Revision.\"", "uuid": "06b. Permit Flow - 2nd Permit Rejected-1669696925", "createdAt": "2025-07-08T14:01:51.862Z", "updatedAt": "2025-10-15T21:56:46.347Z", "startActionId": "3", "nextAvailableActionId": "4", "actions": [{"actionId": "1", "actionTypeVersion": 0, "actionTypeId": "0-5", "connection": {"edgeType": "STANDARD", "nextActionId": "2"}, "fields": {"property_name": "design_status", "value": {"staticValue": "2nd Revision Needed - Rejected by AHJ", "type": "STATIC_VALUE"}}, "type": "SINGLE_CONNECTION"}, {"actionId": "2", "actionTypeVersion": 0, "actionTypeId": "0-8", "fields": {"subject": "2nd Time Permit Rejected - {{ enrolled_object.project_number }}", "body": "<p>{{ enrolled_object.dealname }}</p>\n<p>{{ enrolled_object.ahj }}<br><br>Rejection Reason: {{ enrolled_object.n2nd_permit_rejection_reason }}</p>", "owner_properties": ["rtb_lead"]}, "type": "SINGLE_CONNECTION"}, {"actionId": "3", "actionTypeVersion": 0, "actionTypeId": "0-1", "connection": {"edgeType": "STANDARD", "nextActionId": "1"}, "fields": {"delta": "2", "time_unit": "MINUTES"}, "type": "SINGLE_CONNECTION"}], "enrollmentCriteria": {"shouldReEnroll": true, "listFilterBranch": {"filterBranches": [{"filterBranches": [], "filters": [{"property": "permitting_status", "operation": {"operator": "IS_ANY_OF", "includeObjectsWithNoValueSet": false, "values": ["Rejected 2nd Time - Needs Revisions"], "operationType": "ENUMERATION"}, "filterType": "PROPERTY"}], "filterBranchType": "AND", "filterBranchOperator": "AND"}], "filters": [], "filterBranchType": "OR", "filterBranchOperator": "OR"}, "unEnrollObjectsNotMeetingCriteria": false, "reEnrollmentTriggersFilterBranches": [], "type": "LIST_BASED"}, "timeWindows": [], "blockedDates": [], "customProperties": {}, "dataSources": [{"name": "fetched_object_152976280", "objectTypeId": "0-8", "associationTypeId": 19, "associationCategory": "HUBSPOT_DEFINED", "sortBy": {"property": "hs_lastmodifieddate", "missing": null, "order": "DESC"}, "type": "ASSOCIATION"}, {"name": "fetched_object_152976278", "objectTypeId": "0-1", "associationTypeId": 3, "associationCategory": "HUBSPOT_DEFINED", "type": "ASSOCIATION"}, {"name": "fetched_object_152976279", "objectTypeId": "0-2", "associationTypeId": 341, "associationCategory": "HUBSPOT_DEFINED", "sortBy": {"property": "hs_lastmodifieddate", "missing": null, "order": "DESC"}, "type": "ASSOCIATION"}, {"name": "fetched_object_152976277", "objectTypeId": "0-1", "associationTypeId": 3, "associationCategory": "HUBSPOT_DEFINED", "sortBy": {"property": "hs_lastmodifieddate", "missing": null, "order": "DESC"}, "type": "ASSOCIATION"}], "crmObjectCreationStatus": "COMPLETE", "type": "PLATFORM_FLOW"}