{"id": "1717240382", "isEnabled": true, "objectTypeId": "0-3", "flowType": "WORKFLOW", "revisionId": "5", "name": "PTO First Time Pass 365 Days", "description": "Updates the inspection status to \"Yes\" when the inspection has not failed and has passed.", "createdAt": "2025-11-04T04:45:05.750Z", "updatedAt": "2025-11-04T04:48:57.014Z", "startActionId": "3", "nextAvailableActionId": "4", "actions": [{"actionId": "3", "actionTypeVersion": 0, "actionTypeId": "0-5", "fields": {"property_name": "pto_first_time_pass_", "value": {"staticValue": "true", "type": "STATIC_VALUE"}}, "type": "SINGLE_CONNECTION"}], "enrollmentCriteria": {"shouldReEnroll": false, "listFilterBranch": {"filterBranches": [{"filterBranches": [], "filters": [{"property": "pto_failed_last_365_days", "operation": {"operator": "IS_UNKNOWN", "includeObjectsWithNoValueSet": false, "operationType": "ALL_PROPERTY"}, "filterType": "PROPERTY"}, {"property": "pto_last_365_days", "operation": {"operator": "IS_ANY_OF", "includeObjectsWithNoValueSet": false, "values": ["true"], "operationType": "ENUMERATION"}, "filterType": "PROPERTY"}], "filterBranchType": "AND", "filterBranchOperator": "AND"}], "filters": [], "filterBranchType": "OR", "filterBranchOperator": "OR"}, "unEnrollObjectsNotMeetingCriteria": false, "reEnrollmentTriggersFilterBranches": [], "type": "LIST_BASED"}, "timeWindows": [], "blockedDates": [], "customProperties": {}, "dataSources": [{"name": "fetched_object_208512011", "objectTypeId": "0-1", "associationTypeId": 3, "associationCategory": "HUBSPOT_DEFINED", "type": "ASSOCIATION"}, {"name": "fetched_object_208512009", "objectTypeId": "0-1", "associationTypeId": 3, "associationCategory": "HUBSPOT_DEFINED", "sortBy": {"property": "hs_lastmodifieddate", "missing": null, "order": "DESC"}, "type": "ASSOCIATION"}, {"name": "fetched_object_208512012", "objectTypeId": "0-8", "associationTypeId": 19, "associationCategory": "HUBSPOT_DEFINED", "sortBy": {"property": "hs_lastmodifieddate", "missing": null, "order": "DESC"}, "type": "ASSOCIATION"}, {"name": "fetched_object_208512010", "objectTypeId": "0-2", "associationTypeId": 341, "associationCategory": "HUBSPOT_DEFINED", "sortBy": {"property": "hs_lastmodifieddate", "missing": null, "order": "DESC"}, "type": "ASSOCIATION"}], "crmObjectCreationStatus": "COMPLETE", "type": "PLATFORM_FLOW"}