{"id": "1771911697", "isEnabled": true, "objectTypeId": "0-3", "flowType": "WORKFLOW", "revisionId": "5", "name": "Sales Action - LightReach", "description": "Updates deal stage to \"Cancelled\" and clears sales actions when sales actions include \"Cancel Project\" and a cancellation reason is provided.", "createdAt": "2026-02-05T16:43:45.595Z", "updatedAt": "2026-02-05T16:53:00.085Z", "startActionId": "1", "nextAvailableActionId": "3", "actions": [{"actionId": "1", "actionTypeVersion": 0, "actionTypeId": "0-5", "connection": {"edgeType": "STANDARD", "nextActionId": "2"}, "fields": {"property_name": "dealstage", "value": {"staticValue": "closedwon", "type": "STATIC_VALUE"}}, "type": "SINGLE_CONNECTION"}, {"actionId": "2", "actionTypeVersion": 0, "actionTypeId": "0-5", "fields": {"property_name": "sales_actions", "value": {"staticValue": "", "type": "STATIC_VALUE"}}, "type": "SINGLE_CONNECTION"}], "enrollmentCriteria": {"shouldReEnroll": true, "listFilterBranch": {"filterBranches": [{"filterBranches": [], "filters": [{"property": "sales_actions", "operation": {"operator": "IS_ANY_OF", "includeObjectsWithNoValueSet": false, "values": ["LightReach Order Confirmed"], "operationType": "ENUMERATION"}, "filterType": "PROPERTY"}, {"property": "payment_method", "operation": {"operator": "IS_EXACTLY", "includeObjectsWithNoValueSet": false, "values": ["Lightreach"], "operationType": "ENUMERATION"}, "filterType": "PROPERTY"}], "filterBranchType": "AND", "filterBranchOperator": "AND"}], "filters": [], "filterBranchType": "OR", "filterBranchOperator": "OR"}, "unEnrollObjectsNotMeetingCriteria": false, "reEnrollmentTriggersFilterBranches": [{"filterBranches": [], "filters": [{"property": "hs_name", "operation": {"operator": "IS_EQUAL_TO", "includeObjectsWithNoValueSet": false, "value": "payment_method", "operationType": "STRING"}, "filterType": "PROPERTY"}, {"property": "hs_value", "operation": {"operator": "IS_EXACTLY", "includeObjectsWithNoValueSet": false, "values": ["Lightreach"], "operationType": "ENUMERATION"}, "filterType": "PROPERTY"}], "filterBranchType": "AND", "filterBranchOperator": "AND"}, {"filterBranches": [], "filters": [{"property": "hs_name", "operation": {"operator": "IS_EQUAL_TO", "includeObjectsWithNoValueSet": false, "value": "sales_actions", "operationType": "STRING"}, "filterType": "PROPERTY"}, {"property": "hs_value", "operation": {"operator": "IS_ANY_OF", "includeObjectsWithNoValueSet": false, "values": ["LightReach Order Confirmed"], "operationType": "ENUMERATION"}, "filterType": "PROPERTY"}], "filterBranchType": "AND", "filterBranchOperator": "AND"}], "type": "LIST_BASED"}, "timeWindows": [], "blockedDates": [], "customProperties": {}, "dataSources": [{"name": "fetched_object_262555031", "objectTypeId": "0-1", "associationTypeId": 3, "associationCategory": "HUBSPOT_DEFINED", "type": "ASSOCIATION"}, {"name": "fetched_object_262555028", "objectTypeId": "0-1", "associationTypeId": 3, "associationCategory": "HUBSPOT_DEFINED", "sortBy": {"property": "hs_lastmodifieddate", "missing": null, "order": "DESC"}, "type": "ASSOCIATION"}, {"name": "fetched_object_262555030", "objectTypeId": "0-8", "associationTypeId": 19, "associationCategory": "HUBSPOT_DEFINED", "sortBy": {"property": "hs_lastmodifieddate", "missing": null, "order": "DESC"}, "type": "ASSOCIATION"}, {"name": "fetched_object_262555029", "objectTypeId": "0-2", "associationTypeId": 341, "associationCategory": "HUBSPOT_DEFINED", "sortBy": {"property": "hs_lastmodifieddate", "missing": null, "order": "DESC"}, "type": "ASSOCIATION"}], "crmObjectCreationStatus": "COMPLETE", "type": "PLATFORM_FLOW"}