{"id": "1778367524", "isEnabled": true, "objectTypeId": "0-3", "flowType": "WORKFLOW", "revisionId": "4", "name": "Utility Flow - As-Built Resubmitted to Utility", "description": "Updates the Interconnection Status to \"Resubmitted To Utility\" when a related task titled \"Submit Revision to Utility - WMS\" is completed and status is \"Revision Returned From Design.\"", "createdAt": "2026-02-16T21:42:39.482Z", "updatedAt": "2026-02-16T21:48:19.414Z", "startActionId": "1", "nextAvailableActionId": "3", "actions": [{"actionId": "1", "actionTypeVersion": 0, "actionTypeId": "0-5", "connection": {"edgeType": "STANDARD", "nextActionId": "2"}, "fields": {"property_name": "interconnection_status", "value": {"staticValue": "As-Built Resubmitted", "type": "STATIC_VALUE"}}, "type": "SINGLE_CONNECTION"}, {"actionId": "2", "actionTypeVersion": 0, "actionTypeId": "0-5", "fields": {"property_name": "interconnections_resubmit_date", "value": {"timestampType": "EXECUTION_TIME", "type": "TIMESTAMP"}}, "type": "SINGLE_CONNECTION"}], "enrollmentCriteria": {"shouldReEnroll": false, "listFilterBranch": {"filterBranches": [{"filterBranches": [{"filterBranches": [], "filters": [{"property": "hs_task_subject", "operation": {"operator": "IS_EQUAL_TO", "includeObjectsWithNoValueSet": false, "values": ["Submit As-Built Revision to the Utility - ZRS"], "operationType": "MULTISTRING"}, "filterType": "PROPERTY"}, {"property": "hs_task_status", "operation": {"operator": "IS_ANY_OF", "includeObjectsWithNoValueSet": false, "values": ["COMPLETED"], "operationType": "ENUMERATION"}, "filterType": "PROPERTY"}], "objectTypeId": "0-4", "operator": "IN_LIST", "associationTypeId": 11, "associationCategory": "HUBSPOT_DEFINED", "filterBranchType": "ASSOCIATION", "filterBranchOperator": "AND"}], "filters": [{"property": "interconnection_status", "operation": {"operator": "IS_ANY_OF", "includeObjectsWithNoValueSet": false, "values": ["As-Built Ready to Resubmit"], "operationType": "ENUMERATION"}, "filterType": "PROPERTY"}], "filterBranchType": "AND", "filterBranchOperator": "AND"}], "filters": [], "filterBranchType": "OR", "filterBranchOperator": "OR"}, "unEnrollObjectsNotMeetingCriteria": false, "reEnrollmentTriggersFilterBranches": [], "type": "LIST_BASED"}, "timeWindows": [], "blockedDates": [], "customProperties": {}, "dataSources": [{"name": "fetched_object_269718043", "objectTypeId": "0-1", "associationTypeId": 3, "associationCategory": "HUBSPOT_DEFINED", "type": "ASSOCIATION"}, {"name": "fetched_object_269718042", "objectTypeId": "0-8", "associationTypeId": 19, "associationCategory": "HUBSPOT_DEFINED", "sortBy": {"property": "hs_lastmodifieddate", "missing": null, "order": "DESC"}, "type": "ASSOCIATION"}, {"name": "fetched_object_269718045", "objectTypeId": "0-2", "associationTypeId": 341, "associationCategory": "HUBSPOT_DEFINED", "sortBy": {"property": "hs_lastmodifieddate", "missing": null, "order": "DESC"}, "type": "ASSOCIATION"}, {"name": "fetched_object_269718044", "objectTypeId": "0-1", "associationTypeId": 3, "associationCategory": "HUBSPOT_DEFINED", "sortBy": {"property": "hs_lastmodifieddate", "missing": null, "order": "DESC"}, "type": "ASSOCIATION"}], "crmObjectCreationStatus": "COMPLETE", "type": "PLATFORM_FLOW"}