{"id": "229154643", "isEnabled": true, "objectTypeId": "0-3", "flowType": "WORKFLOW", "revisionId": "362", "name": "Assignments | Project Team", "description": "Assigns project team leads based on project location, utility company, customer type, and stage for active projects excluding cancelled or completed ones.", "uuid": "Project Assignments-229154643", "createdAt": "2022-07-15T15:26:12.883Z", "updatedAt": "2026-06-19T15:34:02.288Z", "startActionId": "130", "nextAvailableActionId": "249", "actions": [{"actionId": "1", "inputValue": {"propertyName": "pb_location", "type": "OBJECT_PROPERTY"}, "staticBranches": [{"branchValue": "Westminster", "connection": {"edgeType": "STANDARD", "nextActionId": "7"}}, {"branchValue": "Centennial", "connection": {"edgeType": "STANDARD", "nextActionId": "14"}}, {"branchValue": "Colorado Springs", "connection": {"edgeType": "STANDARD", "nextActionId": "28"}}], "defaultBranchName": "", "type": "STATIC_BRANCH"}, {"actionId": "7", "actionTypeVersion": 0, "actionTypeId": "0-5", "connection": {"edgeType": "STANDARD", "nextActionId": "33"}, "fields": {"property_name": "inspections_lead", "value": {"staticValue": "216569621", "type": "STATIC_VALUE"}}, "type": "SINGLE_CONNECTION"}, {"actionId": "14", "actionTypeVersion": 0, "actionTypeId": "0-5", "connection": {"edgeType": "STANDARD", "nextActionId": "34"}, "fields": {"property_name": "inspections_lead", "value": {"staticValue": "216569623", "type": "STATIC_VALUE"}}, "type": "SINGLE_CONNECTION"}, {"actionId": "28", "actionTypeVersion": 0, "actionTypeId": "0-5", "connection": {"edgeType": "STANDARD", "nextActionId": "36"}, "fields": {"property_name": "inspections_lead", "value": {"staticValue": "216569620", "type": "STATIC_VALUE"}}, "type": "SINGLE_CONNECTION"}, {"actionId": "33", "actionTypeVersion": 0, "actionTypeId": "0-5", "fields": {"property_name": "operations_manager", "value": {"staticValue": "216569627", "type": "STATIC_VALUE"}}, "type": "SINGLE_CONNECTION"}, {"actionId": "34", "actionTypeVersion": 0, "actionTypeId": "0-5", "fields": {"property_name": "operations_manager", "value": {"staticValue": "216569618", "type": "STATIC_VALUE"}}, "type": "SINGLE_CONNECTION"}, {"actionId": "36", "actionTypeVersion": 0, "actionTypeId": "0-5", "fields": {"property_name": "operations_manager", "value": {"staticValue": "216569620", "type": "STATIC_VALUE"}}, "type": "SINGLE_CONNECTION"}, {"actionId": "68", "actionTypeVersion": 0, "actionTypeId": "0-5", "connection": {"edgeType": "STANDARD", "nextActionId": "75"}, "fields": {"property_name": "permit_tech", "value": {"staticValue": "78035785", "type": "STATIC_VALUE"}}, "type": "SINGLE_CONNECTION"}, {"actionId": "75", "actionTypeVersion": 0, "actionTypeId": "0-5", "connection": {"edgeType": "STANDARD", "nextActionId": "83"}, "fields": {"property_name": "interconnections_tech", "value": {"staticValue": "78035785", "type": "STATIC_VALUE"}}, "type": "SINGLE_CONNECTION"}, {"actionId": "83", "actionTypeVersion": 0, "actionTypeId": "0-5", "connection": {"edgeType": "STANDARD", "nextActionId": "1"}, "fields": {"property_name": "site_survey_scheduler", "value": {"propertyName": "project_manager", "type": "OBJECT_PROPERTY"}}, "type": "SINGLE_CONNECTION"}, {"actionId": "90", "listBranches": [{"filterBranch": {"filterBranches": [{"filterBranches": [], "filters": [{"property": "tags", "operation": {"operator": "IS_ANY_OF", "includeObjectsWithNoValueSet": false, "values": ["Commercial", "Waiting on Site Construction"], "operationType": "ENUMERATION"}, "filterType": "PROPERTY"}, {"property": "pb_location", "operation": {"operator": "IS_ANY_OF", "includeObjectsWithNoValueSet": false, "values": ["Centennial", "Westminster", "Colorado Springs"], "operationType": "ENUMERATION"}, "filterType": "PROPERTY"}], "filterBranchType": "AND", "filterBranchOperator": "AND"}, {"filterBranches": [], "filters": [{"property": "customer_type", "operation": {"operator": "IS_ANY_OF", "includeObjectsWithNoValueSet": false, "values": ["Commercial"], "operationType": "ENUMERATION"}, "filterType": "PROPERTY"}, {"property": "pb_location", "operation": {"operator": "IS_ANY_OF", "includeObjectsWithNoValueSet": false, "values": ["Centennial", "Westminster", "Colorado Springs"], "operationType": "ENUMERATION"}, "filterType": "PROPERTY"}], "filterBranchType": "AND", "filterBranchOperator": "AND"}], "filters": [], "filterBranchType": "OR", "filterBranchOperator": "OR"}, "branchName": "New Construction/Comms", "connection": {"edgeType": "STANDARD", "nextActionId": "93"}}], "defaultBranch": {"edgeType": "STANDARD", "nextActionId": "199"}, "type": "LIST_BRANCH"}, {"actionId": "91", "actionTypeVersion": 0, "actionTypeId": "0-5", "connection": {"edgeType": "STANDARD", "nextActionId": "126"}, "fields": {"property_name": "inspections_lead", "value": {"staticValue": "216569644", "type": "STATIC_VALUE"}}, "type": "SINGLE_CONNECTION"}, {"actionId": "92", "actionTypeVersion": 0, "actionTypeId": "0-5", "connection": {"edgeType": "STANDARD", "nextActionId": "95"}, "fields": {"property_name": "operations_manager", "value": {"staticValue": "216569628", "type": "STATIC_VALUE"}}, "type": "SINGLE_CONNECTION"}, {"actionId": "93", "actionTypeVersion": 0, "actionTypeId": "0-5", "connection": {"edgeType": "STANDARD", "nextActionId": "91"}, "fields": {"property_name": "rtb_lead", "value": {"staticValue": "212300959", "type": "STATIC_VALUE"}}, "type": "SINGLE_CONNECTION"}, {"actionId": "95", "actionTypeVersion": 0, "actionTypeId": "0-5", "connection": {"edgeType": "STANDARD", "nextActionId": "96"}, "fields": {"property_name": "permit_tech", "value": {"staticValue": "78035785", "type": "STATIC_VALUE"}}, "type": "SINGLE_CONNECTION"}, {"actionId": "96", "actionTypeVersion": 0, "actionTypeId": "0-5", "connection": {"edgeType": "STANDARD", "nextActionId": "97"}, "fields": {"property_name": "interconnections_tech", "value": {"staticValue": "78035785", "type": "STATIC_VALUE"}}, "type": "SINGLE_CONNECTION"}, {"actionId": "97", "actionTypeVersion": 0, "actionTypeId": "0-5", "fields": {"property_name": "site_survey_scheduler", "value": {"propertyName": "project_manager", "type": "OBJECT_PROPERTY"}}, "type": "SINGLE_CONNECTION"}, {"actionId": "98", "actionTypeVersion": 0, "actionTypeId": "0-5", "connection": {"edgeType": "STANDARD", "nextActionId": "90"}, "fields": {"property_name": "sgip_lead", "value": {"staticValue": "216565308", "type": "STATIC_VALUE"}}, "type": "SINGLE_CONNECTION"}, {"actionId": "125", "actionTypeVersion": 0, "actionTypeId": "0-5", "connection": {"edgeType": "STANDARD", "nextActionId": "197"}, "fields": {"property_name": "operations_supervisor", "value": {"staticValue": "216569628", "type": "STATIC_VALUE"}}, "type": "SINGLE_CONNECTION"}, {"actionId": "126", "actionTypeVersion": 0, "actionTypeId": "0-5", "connection": {"edgeType": "STANDARD", "nextActionId": "92"}, "fields": {"property_name": "operations_supervisor", "value": {"staticValue": "216569628", "type": "STATIC_VALUE"}}, "type": "SINGLE_CONNECTION"}, {"actionId": "130", "actionTypeVersion": 0, "actionTypeId": "0-1", "connection": {"edgeType": "STANDARD", "nextActionId": "195"}, "fields": {"delta": "3", "time_unit": "MINUTES"}, "type": "SINGLE_CONNECTION"}, {"actionId": "195", "actionTypeVersion": 0, "actionTypeId": "0-11", "connection": {"edgeType": "STANDARD", "nextActionId": "198"}, "fields": {"user_ids": ["91474150", "85273950"], "target_property": "design", "overwrite_current_owner": "false"}, "type": "SINGLE_CONNECTION"}, {"actionId": "197", "actionTypeVersion": 0, "actionTypeId": "0-5", "connection": {"edgeType": "STANDARD", "nextActionId": "68"}, "fields": {"property_name": "rtb_lead", "value": {"propertyName": "project_manager", "type": "OBJECT_PROPERTY"}}, "type": "SINGLE_CONNECTION"}, {"actionId": "198", "actionTypeVersion": 0, "actionTypeId": "0-5", "connection": {"edgeType": "STANDARD", "nextActionId": "98"}, "fields": {"property_name": "tech_ops_lead", "value": {"staticValue": "2068088473", "type": "STATIC_VALUE"}}, "type": "SINGLE_CONNECTION"}, {"actionId": "199", "listBranches": [{"filterBranch": {"filterBranches": [{"filterBranches": [], "filters": [{"property": "pb_location", "operation": {"operator": "IS_ANY_OF", "includeObjectsWithNoValueSet": false, "values": ["Centennial", "Westminster", "Colorado Springs"], "operationType": "ENUMERATION"}, "filterType": "PROPERTY"}], "filterBranchType": "AND", "filterBranchOperator": "AND"}], "filters": [], "filterBranchType": "OR", "filterBranchOperator": "OR"}, "branchName": "Colorado", "connection": {"edgeType": "STANDARD", "nextActionId": "125"}}, {"filterBranch": {"filterBranches": [{"filterBranches": [], "filters": [{"property": "pb_location", "operation": {"operator": "IS_ANY_OF", "includeObjectsWithNoValueSet": false, "values": ["San Luis Obispo", "Camarillo"], "operationType": "ENUMERATION"}, "filterType": "PROPERTY"}], "filterBranchType": "AND", "filterBranchOperator": "AND"}], "filters": [], "filterBranchType": "OR", "filterBranchOperator": "OR"}, "branchName": "California", "connection": {"edgeType": "STANDARD", "nextActionId": "201"}}], "type": "LIST_BRANCH"}, {"actionId": "200", "actionTypeVersion": 0, "actionTypeId": "0-5", "fields": {"property_name": "interconnections_tech", "value": {"staticValue": "212300376", "type": "STATIC_VALUE"}}, "type": "SINGLE_CONNECTION"}, {"actionId": "201", "actionTypeVersion": 0, "actionTypeId": "0-5", "connection": {"edgeType": "STANDARD", "nextActionId": "218"}, "fields": {"property_name": "operations_supervisor", "value": {"staticValue": "212300376", "type": "STATIC_VALUE"}}, "type": "SINGLE_CONNECTION"}, {"actionId": "202", "inputValue": {"propertyName": "pb_location", "type": "OBJECT_PROPERTY"}, "staticBranches": [{"branchValue": "San Luis Obispo", "connection": {"edgeType": "STANDARD", "nextActionId": "213"}}, {"branchValue": "Camarillo", "connection": {"edgeType": "STANDARD", "nextActionId": "221"}}], "defaultBranchName": "", "type": "STATIC_BRANCH"}, {"actionId": "204", "actionTypeVersion": 0, "actionTypeId": "0-5", "fields": {"property_name": "interconnections_tech", "value": {"staticValue": "212300376", "type": "STATIC_VALUE"}}, "type": "SINGLE_CONNECTION"}, {"actionId": "208", "actionTypeVersion": 0, "actionTypeId": "0-5", "connection": {"edgeType": "STANDARD", "nextActionId": "226"}, "fields": {"property_name": "operations_manager", "value": {"staticValue": "216569641", "type": "STATIC_VALUE"}}, "type": "SINGLE_CONNECTION"}, {"actionId": "210", "actionTypeVersion": 0, "actionTypeId": "0-5", "fields": {"property_name": "interconnections_tech", "value": {"staticValue": "216565308", "type": "STATIC_VALUE"}}, "type": "SINGLE_CONNECTION"}, {"actionId": "213", "listBranches": [{"filterBranch": {"filterBranches": [{"filterBranches": [], "filters": [{"property": "utility_company", "operation": {"operator": "IS_ANY_OF", "includeObjectsWithNoValueSet": false, "values": ["PG&E"], "operationType": "ENUMERATION"}, "filterType": "PROPERTY"}], "filterBranchType": "AND", "filterBranchOperator": "AND"}], "filters": [], "filterBranchType": "OR", "filterBranchOperator": "OR"}, "branchName": "PGE", "connection": {"edgeType": "STANDARD", "nextActionId": "210"}}, {"filterBranch": {"filterBranches": [{"filterBranches": [], "filters": [{"property": "utility_company", "operation": {"operator": "IS_ANY_OF", "includeObjectsWithNoValueSet": false, "values": ["SCE"], "operationType": "ENUMERATION"}, "filterType": "PROPERTY"}], "filterBranchType": "AND", "filterBranchOperator": "AND"}], "filters": [], "filterBranchType": "OR", "filterBranchOperator": "OR"}, "branchName": "SCE", "connection": {"edgeType": "STANDARD", "nextActionId": "216"}}], "defaultBranch": {"edgeType": "STANDARD", "nextActionId": "200"}, "type": "LIST_BRANCH"}, {"actionId": "216", "actionTypeVersion": 0, "actionTypeId": "0-5", "fields": {"property_name": "interconnections_tech", "value": {"staticValue": "395832312", "type": "STATIC_VALUE"}}, "type": "SINGLE_CONNECTION"}, {"actionId": "218", "actionTypeVersion": 0, "actionTypeId": "0-5", "connection": {"edgeType": "STANDARD", "nextActionId": "208"}, "fields": {"property_name": "inspections_lead", "value": {"staticValue": "82957883", "type": "STATIC_VALUE"}}, "type": "SINGLE_CONNECTION"}, {"actionId": "221", "listBranches": [{"filterBranch": {"filterBranches": [{"filterBranches": [], "filters": [{"property": "utility_company", "operation": {"operator": "IS_ANY_OF", "includeObjectsWithNoValueSet": false, "values": ["PG&E"], "operationType": "ENUMERATION"}, "filterType": "PROPERTY"}], "filterBranchType": "AND", "filterBranchOperator": "AND"}], "filters": [], "filterBranchType": "OR", "filterBranchOperator": "OR"}, "branchName": "PGE", "connection": {"edgeType": "STANDARD", "nextActionId": "223"}}, {"filterBranch": {"filterBranches": [{"filterBranches": [], "filters": [{"property": "utility_company", "operation": {"operator": "IS_ANY_OF", "includeObjectsWithNoValueSet": false, "values": ["SCE"], "operationType": "ENUMERATION"}, "filterType": "PROPERTY"}], "filterBranchType": "AND", "filterBranchOperator": "AND"}], "filters": [], "filterBranchType": "OR", "filterBranchOperator": "OR"}, "branchName": "SCE", "connection": {"edgeType": "STANDARD", "nextActionId": "224"}}], "defaultBranch": {"edgeType": "STANDARD", "nextActionId": "204"}, "type": "LIST_BRANCH"}, {"actionId": "223", "actionTypeVersion": 0, "actionTypeId": "0-5", "fields": {"property_name": "interconnections_tech", "value": {"staticValue": "216565308", "type": "STATIC_VALUE"}}, "type": "SINGLE_CONNECTION"}, {"actionId": "224", "actionTypeVersion": 0, "actionTypeId": "0-5", "fields": {"property_name": "interconnections_tech", "value": {"staticValue": "395832312", "type": "STATIC_VALUE"}}, "type": "SINGLE_CONNECTION"}, {"actionId": "226", "actionTypeVersion": 0, "actionTypeId": "0-5", "connection": {"edgeType": "STANDARD", "nextActionId": "246"}, "fields": {"property_name": "rtb_lead", "value": {"staticValue": "212300376", "type": "STATIC_VALUE"}}, "type": "SINGLE_CONNECTION"}, {"actionId": "246", "actionTypeVersion": 0, "actionTypeId": "0-5", "connection": {"edgeType": "STANDARD", "nextActionId": "247"}, "fields": {"property_name": "permit_tech", "value": {"staticValue": "82539445", "type": "STATIC_VALUE"}}, "type": "SINGLE_CONNECTION"}, {"actionId": "247", "actionTypeVersion": 0, "actionTypeId": "0-5", "connection": {"edgeType": "STANDARD", "nextActionId": "202"}, "fields": {"property_name": "site_survey_scheduler", "value": {"staticValue": "212300376", "type": "STATIC_VALUE"}}, "type": "SINGLE_CONNECTION"}], "enrollmentCriteria": {"shouldReEnroll": true, "listFilterBranch": {"filterBranches": [{"filterBranches": [], "filters": [{"property": "pb_location", "operation": {"operator": "IS_KNOWN", "includeObjectsWithNoValueSet": false, "operationType": "ALL_PROPERTY"}, "filterType": "PROPERTY"}, {"property": "pipeline", "operation": {"operator": "IS_ANY_OF", "includeObjectsWithNoValueSet": false, "values": ["6900017"], "operationType": "ENUMERATION"}, "filterType": "PROPERTY"}, {"property": "dealstage", "operation": {"operator": "IS_NONE_OF", "includeObjectsWithNoValueSet": false, "values": ["52474745", "20440343", "68229433", "68245827", "76979603"], "operationType": "ENUMERATION"}, "filterType": "PROPERTY"}], "filterBranchType": "AND", "filterBranchOperator": "AND"}], "filters": [], "filterBranchType": "OR", "filterBranchOperator": "OR"}, "unEnrollObjectsNotMeetingCriteria": false, "reEnrollmentTriggersFilterBranches": [{"filterBranches": [], "filters": [{"property": "hs_name", "operation": {"operator": "IS_EQUAL_TO", "includeObjectsWithNoValueSet": false, "value": "pb_location", "operationType": "STRING"}, "filterType": "PROPERTY"}, {"property": "hs_value", "operation": {"operator": "IS_KNOWN", "includeObjectsWithNoValueSet": false, "operationType": "ALL_PROPERTY"}, "filterType": "PROPERTY"}], "filterBranchType": "AND", "filterBranchOperator": "AND"}], "type": "LIST_BASED"}, "timeWindows": [], "blockedDates": [], "customProperties": {}, "dataSources": [], "crmObjectCreationStatus": "COMPLETE", "type": "PLATFORM_FLOW"}