{"id": "570449164", "isEnabled": true, "objectTypeId": "0-3", "flowType": "WORKFLOW", "revisionId": "11", "name": "Update AHJ ", "description": "Creates high-priority tasks for project managers or permit leads to fill missing AHJ details on active projects in the pipeline, filtered by location and project status.", "uuid": "Update AHJ -570449164", "createdAt": "2024-04-04T17:33:13.729Z", "updatedAt": "2026-03-27T18:40:54.287Z", "startActionId": "2", "nextAvailableActionId": "4", "actions": [{"actionId": "1", "actionTypeVersion": 0, "actionTypeId": "0-3", "fields": {"task_type": "TODO", "subject": "Missing AHJ - WMS", "body": "<p>Please populate the AHJ for this job to support automation.</p>", "associations": [{"target": {"associationCategory": "HUBSPOT_DEFINED", "associationTypeId": 12}, "value": {"type": "ENROLLED_OBJECT"}}], "use_explicit_associations": "true", "owner_assignment": {"value": {"propertyName": "project_manager", "type": "OBJECT_PROPERTY"}, "type": "CUSTOM"}, "priority": "HIGH"}, "type": "SINGLE_CONNECTION"}, {"actionId": "2", "listBranches": [{"filterBranch": {"filterBranches": [{"filterBranches": [], "filters": [{"property": "pb_location", "operation": {"operator": "IS_ANY_OF", "includeObjectsWithNoValueSet": false, "values": ["San Luis Obispo", "Camarillo"], "operationType": "ENUMERATION"}, "filterType": "PROPERTY"}], "filterBranchType": "AND", "filterBranchOperator": "AND"}], "filters": [], "filterBranchType": "OR", "filterBranchOperator": "OR"}, "branchName": "California", "connection": {"edgeType": "STANDARD", "nextActionId": "3"}}], "defaultBranch": {"edgeType": "STANDARD", "nextActionId": "1"}, "type": "LIST_BRANCH"}, {"actionId": "3", "actionTypeVersion": 0, "actionTypeId": "0-3", "fields": {"task_type": "TODO", "subject": "Missing AHJ - WMS", "body": "<p>Please populate the AHJ for this job to support automation.</p>", "associations": [{"target": {"associationCategory": "HUBSPOT_DEFINED", "associationTypeId": 12}, "value": {"type": "ENROLLED_OBJECT"}}], "use_explicit_associations": "true", "owner_assignment": {"value": {"propertyName": "permit_tech", "type": "OBJECT_PROPERTY"}, "type": "CUSTOM"}, "priority": "HIGH"}, "type": "SINGLE_CONNECTION"}], "enrollmentCriteria": {"shouldReEnroll": false, "listFilterBranch": {"filterBranches": [{"filterBranches": [], "filters": [{"property": "pipeline", "operation": {"operator": "IS_ANY_OF", "includeObjectsWithNoValueSet": false, "values": ["6900017"], "operationType": "ENUMERATION"}, "filterType": "PROPERTY"}, {"property": "dealstage", "operation": {"operator": "IS_NONE_OF", "includeObjectsWithNoValueSet": false, "values": ["20440343", "68229433"], "operationType": "ENUMERATION"}, "filterType": "PROPERTY"}, {"property": "ahj", "operation": {"operator": "IS_UNKNOWN", "includeObjectsWithNoValueSet": false, "operationType": "ALL_PROPERTY"}, "filterType": "PROPERTY"}, {"property": "project_manager", "operation": {"operator": "IS_KNOWN", "includeObjectsWithNoValueSet": false, "operationType": "ALL_PROPERTY"}, "filterType": "PROPERTY"}, {"property": "permit_tech", "operation": {"operator": "IS_KNOWN", "includeObjectsWithNoValueSet": false, "operationType": "ALL_PROPERTY"}, "filterType": "PROPERTY"}], "filterBranchType": "AND", "filterBranchOperator": "AND"}], "filters": [], "filterBranchType": "OR", "filterBranchOperator": "OR"}, "unEnrollObjectsNotMeetingCriteria": false, "reEnrollmentTriggersFilterBranches": [], "type": "LIST_BASED"}, "timeWindows": [], "blockedDates": [], "customProperties": {}, "dataSources": [], "crmObjectCreationStatus": "COMPLETE", "type": "PLATFORM_FLOW"}