{"id": "570698146", "isEnabled": true, "objectTypeId": "0-5", "flowType": "WORKFLOW", "revisionId": "6", "name": "Ticket Acknowledgement", "description": "Please review the ticket details, review previous work done on the home, and contact the homeowner. ", "uuid": "Ticket Acknowledgement-570698146", "createdAt": "2024-04-05T19:03:04.060Z", "updatedAt": "2024-05-20T15:59:21.005Z", "startActionId": "2", "nextAvailableActionId": "3", "actions": [{"actionId": "2", "actionTypeVersion": 0, "actionTypeId": "0-5", "fields": {"property_name": "hs_pipeline_stage", "value": {"staticValue": "2", "type": "STATIC_VALUE"}}, "type": "SINGLE_CONNECTION"}], "enrollmentCriteria": {"shouldReEnroll": false, "listFilterBranch": {"filterBranches": [{"filterBranches": [{"filterBranches": [], "filters": [{"property": "hs_task_subject", "operation": {"operator": "IS_EQUAL_TO", "includeObjectsWithNoValueSet": false, "values": ["Ticket Kickoff - WMS"], "operationType": "MULTISTRING"}, "filterType": "PROPERTY"}, {"property": "hs_task_status", "operation": {"operator": "IS_ANY_OF", "includeObjectsWithNoValueSet": false, "values": ["COMPLETED"], "operationType": "ENUMERATION"}, "filterType": "PROPERTY"}], "objectTypeId": "0-4", "operator": "IN_LIST", "associationTypeId": 17, "associationCategory": "HUBSPOT_DEFINED", "filterBranchType": "ASSOCIATION", "filterBranchOperator": "AND"}], "filters": [{"property": "createdate", "operation": {"operator": "IS_KNOWN", "includeObjectsWithNoValueSet": false, "operationType": "ALL_PROPERTY"}, "filterType": "PROPERTY"}, {"property": "hubspot_owner_id", "operation": {"operator": "IS_KNOWN", "includeObjectsWithNoValueSet": false, "operationType": "ALL_PROPERTY"}, "filterType": "PROPERTY"}, {"property": "hubspot_owner_assigneddate", "operation": {"operator": "IS_KNOWN", "includeObjectsWithNoValueSet": false, "operationType": "ALL_PROPERTY"}, "filterType": "PROPERTY"}, {"property": "hs_pipeline", "operation": {"operator": "IS_ANY_OF", "includeObjectsWithNoValueSet": false, "values": ["0"], "operationType": "ENUMERATION"}, "filterType": "PROPERTY"}, {"property": "hs_pipeline_stage", "operation": {"operator": "IS_ANY_OF", "includeObjectsWithNoValueSet": false, "values": ["1"], "operationType": "ENUMERATION"}, "filterType": "PROPERTY"}], "filterBranchType": "AND", "filterBranchOperator": "AND"}], "filters": [], "filterBranchType": "OR", "filterBranchOperator": "OR"}, "unEnrollObjectsNotMeetingCriteria": false, "reEnrollmentTriggersFilterBranches": [], "type": "LIST_BASED"}, "timeWindows": [], "blockedDates": [], "customProperties": {}, "dataSources": [], "crmObjectCreationStatus": "COMPLETE", "type": "PLATFORM_FLOW"}