{"id": "616759368", "isEnabled": false, "objectTypeId": "0-3", "flowType": "WORKFLOW", "revisionId": "13", "name": "04. Site Survey Flow - DA Review Task", "description": "Creates a medium-priority task to review the site survey when the survey status is completed and the deal is in the project pipeline.", "uuid": "Site Survey Review Task-616759368", "createdAt": "2024-10-04T14:07:29.706Z", "updatedAt": "2025-07-20T02:37:03.021Z", "startActionId": "3", "nextAvailableActionId": "4", "actions": [{"actionId": "3", "actionTypeVersion": 0, "actionTypeId": "0-3", "fields": {"task_type": "TODO", "subject": "Review Site Survey for DA - ZRS", "body": "", "associations": [{"target": {"associationCategory": "HUBSPOT_DEFINED", "associationTypeId": 8}, "value": {"sourceSpec": {"associationCategory": "HUBSPOT_DEFINED", "associationTypeId": 341}, "type": "COPY_ASSOCIATION"}}, {"target": {"associationCategory": "HUBSPOT_DEFINED", "associationTypeId": 12}, "value": {"type": "ENROLLED_OBJECT"}}], "use_explicit_associations": "true", "owner_assignment": {"value": {"staticValue": "2068088473", "type": "STATIC_VALUE"}, "type": "CUSTOM"}, "priority": "MEDIUM"}, "type": "SINGLE_CONNECTION"}], "enrollmentCriteria": {"shouldReEnroll": false, "listFilterBranch": {"filterBranches": [{"filterBranches": [], "filters": [{"property": "site_survey_status", "operation": {"operator": "IS_ANY_OF", "includeObjectsWithNoValueSet": false, "values": ["Completed"], "operationType": "ENUMERATION"}, "filterType": "PROPERTY"}, {"property": "pipeline", "operation": {"operator": "IS_ANY_OF", "includeObjectsWithNoValueSet": false, "values": ["6900017"], "operationType": "ENUMERATION"}, "filterType": "PROPERTY"}], "filterBranchType": "AND", "filterBranchOperator": "AND"}], "filters": [], "filterBranchType": "OR", "filterBranchOperator": "OR"}, "unEnrollObjectsNotMeetingCriteria": false, "reEnrollmentTriggersFilterBranches": [], "type": "LIST_BASED"}, "timeWindows": [], "blockedDates": [], "customProperties": {}, "dataSources": [], "crmObjectCreationStatus": "COMPLETE", "type": "PLATFORM_FLOW"}